<?xml version="1.0" encoding="UTF-8"?>
<con:restMockAction name="/WCFREST/Service.svc/testString" method="GET" resourcePath="/WCFREST/Service.svc/testString" id="bf432c33-9ad4-4736-b638-68b27f76a9ce" xmlns:con="http://eviware.com/soapui/config"><con:settings><con:setting id="bf432c33-9ad4-4736-b638-68b27f76a9cefileName">%2FWCFREST%2FService.svc%2FtestString</con:setting></con:settings><con:defaultResponse>Response 1</con:defaultResponse><con:dispatchStyle>SEQUENCE</con:dispatchStyle><con:dispatchConfig/><con:dispatchPath xsi:nil="true" xmlns:xsi="http://www.w3.org/2001/XMLSchema-instance"/><con:dispatchXPath/><con:response name="Response 1" id="3571f6cb-d2d3-4711-a25b-c21e2d92e596" httpResponseStatus="200" mediaType="application/json" encoding="utf-8" dataSource=""><con:settings/><con:responseContent>"Test String change"</con:responseContent><con:header><con:name>X-AspNet-Version</con:name><con:value>4.0.30319</con:value></con:header><con:header><con:name>Date</con:name><con:value>Tue, 15 Dec 2015 08:22:06 GMT</con:value></con:header><con:header><con:name>X-Powered-By</con:name><con:value>ASP.NET</con:value></con:header><con:header><con:name>Server</con:name><con:value>Microsoft-IIS/7.5</con:value></con:header><con:header><con:name>Cache-Control</con:name><con:value>private</con:value></con:header></con:response></con:restMockAction>