<?xml version="1.0" encoding="UTF-8"?>
<con:resource name="delayResponse" path="delayResponse" id="df4314da-d88a-44c3-ad71-592ef3518164" xmlns:xsi="http://www.w3.org/2001/XMLSchema-instance" xmlns:con="http://eviware.com/soapui/config"><con:settings><con:setting id="df4314da-d88a-44c3-ad71-592ef3518164fileName">delayResponse</con:setting></con:settings><con:parameters/><con:method name="GET" id="3051313f-31f9-4288-8cd8-f0da1c4c2ee3" method="GET"><con:settings/><con:parameters><con:parameter><con:name>t</con:name><con:value xsi:nil="true"/><con:style>QUERY</con:style><con:type xmlns:xs="http://www.w3.org/2001/XMLSchema">xs:integer</con:type><con:default xsi:nil="true"/></con:parameter></con:parameters><con:request name="Request 1" id="fbdc6d9c-0de6-449a-ab7a-2af9c1a2555c" mediaType="application/json"><con:settings/><con:endpoint>http://rapis02.aqa.com.ru</con:endpoint><con:credentials><con:selectedAuthProfile>No Authorization</con:selectedAuthProfile><con:authType>No Authorization</con:authType></con:credentials><con:parameters/></con:request></con:method></con:resource>