<?xml version="1.0" encoding="UTF-8"?>
<con:resource name="testDouble" path="testDouble" id="e14290d7-136c-4ba6-b100-87a4562b3cc3" xmlns:xsi="http://www.w3.org/2001/XMLSchema-instance" xmlns:con="http://eviware.com/soapui/config"><con:settings><con:setting id="e14290d7-136c-4ba6-b100-87a4562b3cc3fileName">testDouble</con:setting></con:settings><con:parameters/><con:method name="GET" id="e2194f8d-81bf-49a1-94f1-5e1f11f87468" method="GET"><con:settings/><con:parameters><con:parameter><con:name>t</con:name><con:value xsi:nil="true"/><con:style>QUERY</con:style><con:type xmlns:xs="http://www.w3.org/2001/XMLSchema">xs:float</con:type><con:default xsi:nil="true"/></con:parameter></con:parameters><con:request name="Request 1" id="7d7406a1-7bc5-49d7-80a9-90d908fbc9ce" mediaType="application/json"><con:settings><con:setting id="com.eviware.soapui.impl.wsdl.WsdlRequest@request-headers">&lt;xml-fragment/></con:setting></con:settings><con:endpoint>http://rapis02.aqa.com.ru</con:endpoint><con:request/><con:originalUri>http://rapis02.aqa.com.ru/WCFREST/Service.svc/testDouble</con:originalUri><con:credentials><con:selectedAuthProfile>No Authorization</con:selectedAuthProfile><con:authType>No Authorization</con:authType></con:credentials><con:jmsConfig JMSDeliveryMode="PERSISTENT"/><con:jmsPropertyConfig/><con:parameters><entry key="t" value="2.3" xmlns="http://eviware.com/soapui/config"/></con:parameters></con:request></con:method></con:resource>